reproducibility_pkg/__init__.py
reproducibility_pkg/main.py
reproducibility_pkg_Vrishab_Commuri-1.0.3.dist-info/LICENSE
reproducibility_pkg_Vrishab_Commuri-1.0.3.dist-info/METADATA
reproducibility_pkg_Vrishab_Commuri-1.0.3.dist-info/WHEEL
reproducibility_pkg_Vrishab_Commuri-1.0.3.dist-info/top_level.txt
reproducibility_pkg_Vrishab_Commuri-1.0.3.dist-info/RECORD
