Metadata-Version: 2.1
Name: reproducibility-pkg-Vrishab-Commuri
Version: 1.0.3
Summary: A small example package demonstrating a computational reproducibility issue
Home-page: https://github.com/vrishabcommuri/computational-reproducibility
Author: Vrishab Commuri
Author-email: vrishabcommuri@gmail.com
License: UNKNOWN
Platform: UNKNOWN
Classifier: Programming Language :: Python :: 3
Classifier: License :: OSI Approved :: MIT License
Classifier: Operating System :: OS Independent
Requires-Python: >=3.6
Requires-Dist: pandas
